mininet.py
umal.py
ratrack/__init__.py
ratrack/convert.py
ratrack/datalogger.py
ratrack/sensor_adc.py
terkin/__init__.py
terkin/backup.py
terkin/configuration.py
terkin/datalogger.py
terkin/device.py
terkin/exception.py
terkin/logging.py
terkin/model.py
terkin/pycom.py
terkin/util.py
terkin/watchdog.py
terkin/api/__init__.py
terkin/api/http.py
terkin/api/udp.py
terkin/driver/__init__.py
terkin/driver/ads1x15_sensor.py
terkin/driver/bme280_sensor.py
terkin/driver/bmp280_sensor.py
terkin/driver/ds18x20_sensor.py
terkin/driver/ds3231_sensor.py
terkin/driver/epsolar_sensor.py
terkin/driver/gpiozero_sensor.py
terkin/driver/gpsd_sensor.py
terkin/driver/hx711_sensor.py
terkin/driver/hx711_temp_compensated_sensor.py
terkin/driver/ina219_sensor.py
terkin/driver/max17043_sensor.py
terkin/driver/piusv_sensor.py
terkin/driver/pytrack_sensor.py
terkin/driver/si7021_sensor.py
terkin/driver/vedirect_sensor.py
terkin/lib/__init__.py
terkin/lib/epsolar.py
terkin/lib/gpsd.py
terkin/lib/hx711.py
terkin/lib/hx711_heisenberg.py
terkin/network/__init__.py
terkin/network/core.py
terkin/network/gprs.py
terkin/network/lora.py
terkin/network/lte.py
terkin/network/wifi.py
terkin/network/ble/__init__.py
terkin/network/ble/pycom.py
terkin/network/ble/util.py
terkin/sensor/__init__.py
terkin/sensor/button.py
terkin/sensor/common.py
terkin/sensor/core.py
terkin/sensor/linux.py
terkin/sensor/scale.py
terkin/sensor/system.py
terkin/sensor/touch.py
terkin/telemetry/__init__.py
terkin/telemetry/core.py
terkin/telemetry/formatter.py
terkin_cpython/__init__.py
terkin_cpython/compat.py
terkin_cpython/main.py
terkin_cpython/util.py
terkin-0.14.0.dist-info/LICENSE
terkin-0.14.0.dist-info/METADATA
terkin-0.14.0.dist-info/WHEEL
terkin-0.14.0.dist-info/dependency_links.txt
terkin-0.14.0.dist-info/entry_points.txt
terkin-0.14.0.dist-info/top_level.txt
terkin-0.14.0.dist-info/RECORD
