Metadata-Version: 2.1
Name: terkin
Version: 0.14.0
Summary: A flexible data logger for MicroPython and CPython
Home-page: https://github.com/hiveeyes/terkin-datalogger
Author: Andreas Motl
Author-email: andreas.motl@terkin.org
License: AGPL 3, EUPL 1.2
Keywords: sensor networks data acquisition transformation daq routing telemetry m2m iot mqtt http
Classifier: Programming Language :: Python
Classifier: Programming Language :: Python :: 3.7
Classifier: Programming Language :: Python :: 3.8
Classifier: Programming Language :: Python :: 3.9
Classifier: Programming Language :: Python :: 3.10
Classifier: Programming Language :: Python :: 3.11
Classifier: Programming Language :: Python :: Implementation :: CPython
Classifier: Programming Language :: Python :: Implementation :: MicroPython
Classifier: License :: OSI Approved :: GNU Affero General Public License v3
Classifier: License :: OSI Approved :: European Union Public Licence 1.2 (EUPL 1.2)
Classifier: Development Status :: 4 - Beta
Classifier: Environment :: Console
Classifier: Intended Audience :: Developers
Classifier: Intended Audience :: Education
Classifier: Intended Audience :: Information Technology
Classifier: Intended Audience :: Manufacturing
Classifier: Intended Audience :: Science/Research
Classifier: Intended Audience :: System Administrators
Classifier: Intended Audience :: Telecommunications Industry
Classifier: Topic :: Communications
Classifier: Topic :: Internet
Classifier: Topic :: Scientific/Engineering :: Atmospheric Science
Classifier: Topic :: Scientific/Engineering :: GIS
Classifier: Topic :: Scientific/Engineering :: Human Machine Interfaces
Classifier: Topic :: Scientific/Engineering :: Information Analysis
Classifier: Topic :: Scientific/Engineering :: Interface Engine/Protocol Translator
Classifier: Topic :: Software Development :: Embedded Systems
Classifier: Topic :: Software Development :: Libraries
Classifier: Topic :: System :: Archiving
Classifier: Topic :: System :: Networking :: Monitoring
Classifier: Topic :: Utilities
Classifier: Operating System :: POSIX
Classifier: Operating System :: Unix
Classifier: Operating System :: MacOS
License-File: LICENSE
Requires-Dist: terkin-micropython-libraries (==0.14.0)
Requires-Dist: esp32-machine-emulator (<2)
Requires-Dist: psutil (<6)
Requires-Dist: requests (<3)
Requires-Dist: click (<8)
Requires-Dist: pyserial (==3.5)
Requires-Dist: gps (<4)
Requires-Dist: Adafruit-Blinka (<6,>=5.4.0)
Requires-Dist: adafruit-circuitpython-busdevice (<5)
Requires-Dist: adafruit-circuitpython-bme280 (<2.6)
Requires-Dist: adafruit-circuitpython-ads1x15 (<2.3)
Requires-Dist: adafruit-circuitpython-si7021 (<3.3)
Requires-Dist: adafruit-circuitpython-bmp280 (<3.3)
Requires-Dist: adafruit-circuitpython-ina219 (<3.5)
Provides-Extra: lorawan
Requires-Dist: pycrypto (<3) ; (python_version <= "3.10") and extra == 'lorawan'
Requires-Dist: pycryptodome (<4) ; (python_version >= "3.11") and extra == 'lorawan'
Provides-Extra: sbc
Requires-Dist: smbus (==1.1.post2) ; extra == 'sbc'
Requires-Dist: spidev (<4) ; extra == 'sbc'
Requires-Dist: rpi-piusv (==0.1.0) ; extra == 'sbc'
Requires-Dist: gpiozero (<2) ; extra == 'sbc'
Provides-Extra: vedirect
Requires-Dist: vedirect (==2.0.0) ; extra == 'vedirect'
